.DS_Store
_sqleet.cpython-38-darwin.so
sqleet/__init__.py
sqleet/dbapi2.py
sqleet/dump.py
pysqleet-31.1.3.dist-info/LICENSE.txt
pysqleet-31.1.3.dist-info/METADATA
pysqleet-31.1.3.dist-info/WHEEL
pysqleet-31.1.3.dist-info/top_level.txt
pysqleet-31.1.3.dist-info/RECORD
