Metadata-Version: 2.1
Name: pysqleet
Version: 31.1.3
Summary: Drop in replacement for the std libs sqlite3 which enables encryption support for sqlite3
Home-page: https://github.com/robertkearns/pysqleet
Author: Robert Kearns
License: MIT
Keywords: sqlite,sqlite3,sqleet,db,database,encryption
Platform: UNKNOWN
Classifier: Development Status :: 4 - Beta
Classifier: License :: OSI Approved :: MIT License
Classifier: Operating System :: Microsoft :: Windows :: Windows 10
Classifier: Operating System :: POSIX :: Linux
Classifier: Operating System :: MacOS
Classifier: Programming Language :: Python :: Implementation :: CPython
Classifier: Programming Language :: Python :: 3 :: Only
Classifier: Programming Language :: Python :: 3.6
Classifier: Programming Language :: Python :: 3.7
Classifier: Programming Language :: Python :: 3.8
Classifier: Intended Audience :: Developers
Classifier: Topic :: Database
Requires-Python: <3.9,>=3.6
License-File: LICENSE.txt
